Metadata-Version: 2.1
Name: Topsis-Gracevera-102116014
Version: 0.1
Requires-Dist: pandas
Requires-Dist: numpy
